lshmm/__init__.py
lshmm/_version.py
lshmm/api.py
lshmm/core.py
lshmm/fb_diploid.py
lshmm/fb_haploid.py
lshmm/jit.py
lshmm/vit_diploid.py
lshmm/vit_haploid.py
lshmm-0.0.8.dist-info/LICENSE
lshmm-0.0.8.dist-info/METADATA
lshmm-0.0.8.dist-info/WHEEL
lshmm-0.0.8.dist-info/top_level.txt
lshmm-0.0.8.dist-info/RECORD
