Metadata-Version: 2.1
Name: lshmm
Version: 0.0.8
License: MIT
Classifier: Topic :: Scientific/Engineering :: Bio-Informatics
Classifier: Development Status :: 2 - Pre-Alpha
Classifier: Intended Audience :: Science/Research
Classifier: License :: OSI Approved :: MIT License
Classifier: Programming Language :: Python :: 3
Requires-Python: >=3.7
License-File: LICENSE
Requires-Dist: numba
